{"success":true,"data":{"ar":[{"date":"2012-04","value":"6684.230957","beyer":"","cf":"99.26609177"},{"date":"2012-05","value":"2450.950439","beyer":"","cf":"99.40953747"},{"date":"2012-06","value":"2817.399658","beyer":"","cf":"99.87990593"},{"date":"2012-07","value":"2080.890137","beyer":"","cf":"99.90325755"},{"date":"2012-08","value":"2887.479736","beyer":"","cf":"99.89158174"},{"date":"2012-09","value":"8173.581055","beyer":"","cf":"99.94829283"},{"date":"2012-10","value":"9014.349609","beyer":"","cf":"99.84988241"},{"date":"2012-11","value":"4381.049316","beyer":"","cf":"100"},{"date":"2012-12","value":"13654.9668","beyer":"","cf":"100"},{"date":"2013-01","value":"8458.71875","beyer":"","cf":"99.63471386"},{"date":"2013-02","value":"18056.33398","beyer":"","cf":"99.99833203"},{"date":"2013-03","value":"6014.569824","beyer":"","cf":"91.75687622"},{"date":"2013-04","value":"25317.87891","beyer":"","cf":"100"},{"date":"2013-05","value":"7309.078613","beyer":"","cf":"99.99833203"},{"date":"2013-06","value":"8842.520508","beyer":"","cf":"99.97331243"},{"date":"2013-07","value":"5845.418945","beyer":"","cf":"99.89825363"},{"date":"2013-08","value":"16791.25781","beyer":"","cf":"100"},{"date":"2013-09","value":"13300.52832","beyer":"","cf":"99.99332811"},{"date":"2013-10","value":"16241.12109","beyer":"","cf":"100"},{"date":"2013-11","value":"11768.94922","beyer":"","cf":"99.94829283"},{"date":"2013-12","value":"31398.79297","beyer":"","cf":"100"},{"date":"2014-01","value":"17056.68945","beyer":"","cf":"100"},{"date":"2014-02","value":"16381.85059","beyer":"","cf":"98.85410238"},{"date":"2014-03","value":"10011.49902","beyer":"","cf":"98.26864377"},{"date":"2014-04","value":"9783.859375","beyer":"","cf":"99.12431405"},{"date":"2014-05","value":"12112.75879","beyer":"","cf":"100"},{"date":"2014-06","value":"14296.22949","beyer":"","cf":"100"},{"date":"2014-07","value":"46617.30078","beyer":"","cf":"99.99332811"},{"date":"2014-08","value":"17697.7207","beyer":"","cf":"99.99499608"},{"date":"2014-09","value":"16831.77148","beyer":"","cf":"99.97831635"},{"date":"2014-10","value":"17567.53906","beyer":"","cf":"99.9249412"},{"date":"2014-11","value":"28942.0293","beyer":"","cf":"99.98332027"},{"date":"2014-12","value":"19637.77344","beyer":"","cf":"100"},{"date":"2015-01","value":"22824.50391","beyer":"","cf":"100"},{"date":"2015-02","value":"40243.61719","beyer":"","cf":"99.90992944"},{"date":"2015-03","value":"18864.68555","beyer":"","cf":"100"},{"date":"2015-04","value":"10189.30469","beyer":"","cf":"100"},{"date":"2015-05","value":"9471.010742","beyer":"","cf":"99.9749804"},{"date":"2015-06","value":"21046.45508","beyer":"","cf":"99.80818308"},{"date":"2015-07","value":"8451.798828","beyer":"","cf":"99.97331243"},{"date":"2015-08","value":"10065.96875","beyer":"","cf":"100"},{"date":"2015-09","value":"12849.98828","beyer":"","cf":"99.98832419"},{"date":"2015-10","value":"32344.93555","beyer":"","cf":"99.98999216"},{"date":"2015-11","value":"26564.81836","beyer":"","cf":"99.96830851"},{"date":"2015-12","value":"42154.89453","beyer":"","cf":"100"},{"date":"2016-01","value":"38393.48047","beyer":"","cf":"100"},{"date":"2016-02","value":"89737.10156","beyer":"","cf":"99.25108001"},{"date":"2016-03","value":"44611.72656","beyer":"","cf":"100"},{"date":"2016-04","value":"46401.25391","beyer":"","cf":"99.99833203"},{"date":"2016-05","value":"47390.74219","beyer":"","cf":"100"},{"date":"2016-06","value":"52858.63672","beyer":"","cf":"100"},{"date":"2016-07","value":"17017.24609","beyer":"","cf":"99.98832419"},{"date":"2016-08","value":"24573.64258","beyer":"","cf":"100"},{"date":"2016-09","value":"33923.51563","beyer":"","cf":"100"},{"date":"2016-10","value":"21036.73047","beyer":"","cf":"100"},{"date":"2016-11","value":"44910.14453","beyer":"","cf":"99.99666405"},{"date":"2016-12","value":"18725.33398","beyer":"","cf":"100"},{"date":"2017-01","value":"47663.36328","beyer":"","cf":"100"},{"date":"2017-02","value":"33233.96484","beyer":"","cf":"99.97164445"},{"date":"2017-03","value":"34409.375","beyer":"","cf":"100"},{"date":"2017-04","value":"27865.20313","beyer":"","cf":"99.98498824"},{"date":"2017-05","value":"19916.50977","beyer":"","cf":"99.99499608"},{"date":"2017-06","value":"16559.37109","beyer":"","cf":"99.9749804"},{"date":"2017-07","value":"23463.08203","beyer":"","cf":"99.98999216"},{"date":"2017-08","value":"20293.25781","beyer":"","cf":"99.99833203"},{"date":"2017-09","value":"27176.66992","beyer":"","cf":"99.84654646"},{"date":"2017-10","value":"35881.74609","beyer":"","cf":"99.90325755"},{"date":"2017-11","value":"24793.33398","beyer":"","cf":"99.56799493"},{"date":"2017-12","value":"26448.63477","beyer":"","cf":"99.97331243"},{"date":"2018-01","value":"55378.01172","beyer":"","cf":"99.92660918"},{"date":"2018-02","value":"31451.80859","beyer":"","cf":"100"},{"date":"2018-03","value":"31401.81641","beyer":"","cf":"99.89825363"},{"date":"2018-04","value":"29290.05078","beyer":"","cf":"99.99666405"},{"date":"2018-05","value":"28548.8457","beyer":"","cf":"99.99499608"},{"date":"2018-06","value":"22465.72656","beyer":"","cf":"99.99499608"},{"date":"2018-07","value":"27781.41211","beyer":"","cf":"100"},{"date":"2018-08","value":"19026.10938","beyer":"","cf":"99.98832419"},{"date":"2018-09","value":"24287.05078","beyer":"","cf":"99.99332811"},{"date":"2018-10","value":"25002.11328","beyer":"","cf":"99.91493336"},{"date":"2018-11","value":"34821.76172","beyer":"","cf":"99.98165229"},{"date":"2018-12","value":"23630.17969","beyer":"","cf":"99.88991377"},{"date":"2019-01","value":"4964.379395","beyer":"","cf":"100"},{"date":"2019-02","value":"7025.259766","beyer":"","cf":"99.97831635"},{"date":"2019-03","value":"5952.370117","beyer":"","cf":"100"},{"date":"2019-04","value":"10516.90918","beyer":"","cf":"99.96330459"},{"date":"2019-05","value":"8088.811035","beyer":"","cf":"99.90158958"},{"date":"2019-06","value":"8505.839844","beyer":"","cf":"100"},{"date":"2019-07","value":"7145.600098","beyer":"","cf":"100"},{"date":"2019-08","value":"7337.737793","beyer":"","cf":"99.98832419"},{"date":"2019-09","value":"10629.39063","beyer":"","cf":"99.99666405"},{"date":"2019-10","value":"13690.23145","beyer":"","cf":"99.99666405"},{"date":"2019-11","value":"11647.04004","beyer":"","cf":"99.4512368"},{"date":"2019-12","value":"6880.360352","beyer":"","cf":"100"},{"date":"2020-01","value":"3687.030029","beyer":"","cf":"99.99833203"},{"date":"2020-02","value":"13726.90137","beyer":"","cf":"100"},{"date":"2020-03","value":"14537.34961","beyer":"","cf":"100"},{"date":"2020-04","value":"20765.71875","beyer":"","cf":"99.98665733"},{"date":"2020-05","value":"13949.12793","beyer":"","cf":"100"},{"date":"2020-06","value":"13423.08008","beyer":"","cf":"99.98498949"},{"date":"2020-07","value":"9648.859375","beyer":"","cf":"97.62833984"},{"date":"2020-08","value":"12941.0752","beyer":"","cf":"99.99833203"},{"date":"2020-09","value":"17123.78711","beyer":"","cf":"99.99830456"},{"date":"2020-10","value":"15789.84668","beyer":"","cf":"99.99347908"},{"date":"2020-11","value":"22493.57617","beyer":"","cf":"99.99993479"},{"date":"2020-12","value":"14483.521484375","beyer":"","cf":"99.9983697689963"}],"cf":[{"date":"2012-04","value":"99.26609177"},{"date":"2012-05","value":"99.40953747"},{"date":"2012-06","value":"99.87990593"},{"date":"2012-07","value":"99.90325755"},{"date":"2012-08","value":"99.89158174"},{"date":"2012-09","value":"99.94829283"},{"date":"2012-10","value":"99.84988241"},{"date":"2012-11","value":"100"},{"date":"2012-12","value":"100"},{"date":"2013-01","value":"99.63471386"},{"date":"2013-02","value":"99.99833203"},{"date":"2013-03","value":"91.75687622"},{"date":"2013-04","value":"100"},{"date":"2013-05","value":"99.99833203"},{"date":"2013-06","value":"99.97331243"},{"date":"2013-07","value":"99.89825363"},{"date":"2013-08","value":"100"},{"date":"2013-09","value":"99.99332811"},{"date":"2013-10","value":"100"},{"date":"2013-11","value":"99.94829283"},{"date":"2013-12","value":"100"},{"date":"2014-01","value":"100"},{"date":"2014-02","value":"98.85410238"},{"date":"2014-03","value":"98.26864377"},{"date":"2014-04","value":"99.12431405"},{"date":"2014-05","value":"100"},{"date":"2014-06","value":"100"},{"date":"2014-07","value":"99.99332811"},{"date":"2014-08","value":"99.99499608"},{"date":"2014-09","value":"99.97831635"},{"date":"2014-10","value":"99.9249412"},{"date":"2014-11","value":"99.98332027"},{"date":"2014-12","value":"100"},{"date":"2015-01","value":"100"},{"date":"2015-02","value":"99.90992944"},{"date":"2015-03","value":"100"},{"date":"2015-04","value":"100"},{"date":"2015-05","value":"99.9749804"},{"date":"2015-06","value":"99.80818308"},{"date":"2015-07","value":"99.97331243"},{"date":"2015-08","value":"100"},{"date":"2015-09","value":"99.98832419"},{"date":"2015-10","value":"99.98999216"},{"date":"2015-11","value":"99.96830851"},{"date":"2015-12","value":"100"},{"date":"2016-01","value":"100"},{"date":"2016-02","value":"99.25108001"},{"date":"2016-03","value":"100"},{"date":"2016-04","value":"99.99833203"},{"date":"2016-05","value":"100"},{"date":"2016-06","value":"100"},{"date":"2016-07","value":"99.98832419"},{"date":"2016-08","value":"100"},{"date":"2016-09","value":"100"},{"date":"2016-10","value":"100"},{"date":"2016-11","value":"99.99666405"},{"date":"2016-12","value":"100"},{"date":"2017-01","value":"100"},{"date":"2017-02","value":"99.97164445"},{"date":"2017-03","value":"100"},{"date":"2017-04","value":"99.98498824"},{"date":"2017-05","value":"99.99499608"},{"date":"2017-06","value":"99.9749804"},{"date":"2017-07","value":"99.98999216"},{"date":"2017-08","value":"99.99833203"},{"date":"2017-09","value":"99.84654646"},{"date":"2017-10","value":"99.90325755"},{"date":"2017-11","value":"99.56799493"},{"date":"2017-12","value":"99.97331243"},{"date":"2018-01","value":"99.92660918"},{"date":"2018-02","value":"100"},{"date":"2018-03","value":"99.89825363"},{"date":"2018-04","value":"99.99666405"},{"date":"2018-05","value":"99.99499608"},{"date":"2018-06","value":"99.99499608"},{"date":"2018-07","value":"100"},{"date":"2018-08","value":"99.98832419"},{"date":"2018-09","value":"99.99332811"},{"date":"2018-10","value":"99.91493336"},{"date":"2018-11","value":"99.98165229"},{"date":"2018-12","value":"99.88991377"},{"date":"2019-01","value":"100"},{"date":"2019-02","value":"99.97831635"},{"date":"2019-03","value":"100"},{"date":"2019-04","value":"99.96330459"},{"date":"2019-05","value":"99.90158958"},{"date":"2019-06","value":"100"},{"date":"2019-07","value":"100"},{"date":"2019-08","value":"99.98832419"},{"date":"2019-09","value":"99.99666405"},{"date":"2019-10","value":"99.99666405"},{"date":"2019-11","value":"99.4512368"},{"date":"2019-12","value":"100"},{"date":"2020-01","value":"99.99833203"},{"date":"2020-02","value":"100"},{"date":"2020-03","value":"100"},{"date":"2020-04","value":"99.98665733"},{"date":"2020-05","value":"100"},{"date":"2020-06","value":"99.98498949"},{"date":"2020-07","value":"97.62833984"},{"date":"2020-08","value":"99.99833203"},{"date":"2020-09","value":"99.99830456"},{"date":"2020-10","value":"99.99347908"},{"date":"2020-11","value":"99.99993479"},{"date":"2020-12","value":"99.9983697689963"}],"adminNumber":"VUT","area":"310.618"}}
